setup.py
libTest01/__init__.py
libTest01/mod01.py
libTest01/mod02.py
libTest01.egg-info/PKG-INFO
libTest01.egg-info/SOURCES.txt
libTest01.egg-info/dependency_links.txt
libTest01.egg-info/top_level.txt