Metadata-Version: 2.1
Name: libTest01
Version: 0.1
Summary: Una librería de ejemplo en Python
Home-page: https://github.com/tuusuario/mi_libreria
Author: Serk_Black
Author-email: serzap85@gmail.com
License: MIT
